termtinty/__init__.py
termtinty/color.py
termtinty/py.typed
termtinty/tinty.py
termtinty-0.1.0.dist-info/WHEEL
termtinty-0.1.0.dist-info/METADATA
termtinty-0.1.0.dist-info/RECORD
