Metadata-Version: 2.3
Name: termtinty
Version: 0.1.0
Summary: A fluid and lightweight terminal colorizer for Python.
Keywords: terminal,color,ansi,fluent,chaining,cli,tui
Author: m4cky
License: MIT
Classifier: Development Status :: 4 - Beta
Classifier: Intended Audience :: Developers
Classifier: License :: OSI Approved :: MIT License
Classifier: Operating System :: OS Independent
Classifier: Programming Language :: Python :: 3
Classifier: Programming Language :: Python :: 3.13
Classifier: Topic :: Software Development :: Libraries :: Python Modules
Classifier: Topic :: Terminals
Classifier: Typing :: Typed
Requires-Python: >=3.13
Project-URL: Homepage, https://github.com/m4ck-y/py_termtinty
Project-URL: Issues, https://github.com/m4ck-y/py_termtinty/issues
Project-URL: Repository, https://github.com/m4ck-y/py_termtinty
